pytdxwrapper/__init__.py
pytdxwrapper/base.py
pytdxwrapper/config.py
pytdxwrapper/mock.py
pytdxwrapper/py.typed
pytdxwrapper-20250217.dist-info/METADATA
pytdxwrapper-20250217.dist-info/WHEEL
pytdxwrapper-20250217.dist-info/licenses/LICENSE
pytdxwrapper-20250217.dist-info/RECORD
